optimus/__init__.py
optimus/training_setup.py
optimus/actions_lib/__init__.py
optimus/actions_lib/actions.py
optimus/actions_lib/base_actions.py
optimus/agent_lib/__init__.py
optimus/agent_lib/agents.py
optimus/agent_lib/base_agent.py
optimus/agent_lib/tabnet.py
optimus/data_pipeline_lib/__init__.py
optimus/data_pipeline_lib/base_data_pipeline.py
optimus/data_pipeline_lib/data_pipelines.py
optimus/preprocessing_lib/__init__.py
optimus/preprocessing_lib/base_preprocessing.py
optimus/reward_lib/__init__.py
optimus/reward_lib/base_reward.py
optimus/reward_lib/rewards.py
optimus/trainer_lib/__init__.py
optimus/trainer_lib/base_trainer.py
optimus/trainer_lib/losses.py
optimus/trainer_lib/optimizers.py
optimus/trainer_lib/schedules.py
optimus/trainer_lib/trainers.py
gtech_optimus-0.0.7.dist-info/LICENSE
gtech_optimus-0.0.7.dist-info/METADATA
gtech_optimus-0.0.7.dist-info/WHEEL
gtech_optimus-0.0.7.dist-info/top_level.txt
gtech_optimus-0.0.7.dist-info/RECORD
