Metadata-Version: 2.1
Name: gtech-optimus
Version: 0.0.7
Summary: Optimus library for real-time marketing personalization using RL.
Home-page: https://github.com/google-marketing-solutions/optimus
Author: Google gTech Ads EMEA Privacy Data Science Team
License: MIT
Keywords: 1pd privacy reinforcement learning optimization personalization
Classifier: Intended Audience :: Developers
Classifier: Intended Audience :: Science/Research
Classifier: License :: OSI Approved :: Apache Software License
Classifier: Topic :: Scientific/Engineering :: Artificial Intelligence
Requires-Python: >=3.10
License-File: LICENSE
Requires-Dist: jax >=0.4.20
Requires-Dist: ml-collections >=0.1.1
Requires-Dist: tensorflow >=2.11.0
Requires-Dist: flax >=0.7.5
Requires-Dist: numpy ==1.24.1
Requires-Dist: optax >=0.1.7
Requires-Dist: tqdm >=4.66.1
Requires-Dist: orbax-checkpoint ==0.4.2
Requires-Dist: portpicker >=1.5.2
